{
  "$schema": "./node_modules/@angular/cli/lib/config/schema.json",
  "project": {
    "name": "santa-app"
  },
  "apps": [
    {
      "root": "src",
      "outDir": "dist",
      "assets": [
        "assets"
      ],
      "index": "index.html",
      "main": "main.ts",
      "polyfills": "polyfills.ts",
      "test": "test.ts",
      "tsconfig": "tsconfig.app.json",
      "prefix": "santa",
      "styles": [
        "../node_modules/materialize-css/dist/css/materialize.css",
        "../node_modules/materialize-social/materialize-social.css",
        "./app/styles/main.scss"
      ],
      "scripts": [
        "../node_modules/jquery/dist/jquery.js",
        "../node_modules/materialize-css/dist/js/materialize.js",
        "../node_modules/crypto-js/crypto-js.js"
      ],
      "environmentSource": "environments/environment.ts",
      "environments": {
        "dev": "environments/environment.ts",
        "prod": "environments/environment.prod.ts"
      }
    }
  ],
  "lint": [
    {
      "project": "src/tsconfig.app.json",
      "exclude": "**/node_modules/**"
    }
  ],
  "defaults": {
    "styleExt": "scss",
    "component": {}
  }
}
